Metadata-Version: 2.1
Name: diegobmota_image_process
Version: 0.0.1
Summary: Pacote para Processamento de imagens
Home-page: https://github.com/diegobritom
Author: Diego Brito
Author-email: 
Requires-Python: >=3.8
Requires-Dist: numpy
Requires-Dist: scikit-image >=0.16.1
Requires-Dist: matplotlib
